tiupy/__init__.py
tiupy/tiu.py
tiupy/utils/__init__.py
tiupy/utils/header.py
tiupy/utils/objects.py
tiupy-1.1.2.dist-info/LICENSE
tiupy-1.1.2.dist-info/METADATA
tiupy-1.1.2.dist-info/WHEEL
tiupy-1.1.2.dist-info/top_level.txt
tiupy-1.1.2.dist-info/RECORD
