Metadata-Version: 2.1
Name: tiupy
Version: 1.1.2
Summary: A robust web scraper and API wrapper for TIU student system
Home-page: https://github.com/heromr/tiupy
Author: HeroMR
License: MIT
Keywords: tiu uni,tishk university,tiu scraper,tiu API,university system
Classifier: Development Status :: 5 - Production/Stable
Classifier: Intended Audience :: Developers
Classifier: License :: OSI Approved :: MIT License
Classifier: Programming Language :: Python :: 3
Classifier: Operating System :: OS Independent
Requires-Python: >=3.6
License-File: LICENSE
Requires-Dist: httpx (>=0.24.1)
Requires-Dist: beautifulsoup4 (>=4.12.2)
